clac/__init__.py
clac/__version__.py
clac/core.py
clac/exceptions.py
clac/layers.py
clac/py.typed
clac-1.2.0.dist-info/LICENSE
clac-1.2.0.dist-info/METADATA
clac-1.2.0.dist-info/WHEEL
clac-1.2.0.dist-info/top_level.txt
clac-1.2.0.dist-info/RECORD
